assher/__conf__.py
assher/__init__.py
assher/__main__.py
assher-0.7.6.dist-info/LICENSE
assher-0.7.6.dist-info/METADATA
assher-0.7.6.dist-info/WHEEL
assher-0.7.6.dist-info/top_level.txt
assher-0.7.6.dist-info/RECORD
