Metadata-Version: 2.1
Name: assher
Version: 0.7.6
Summary: Async SSH/SFTP massive runner
Home-page: https://github.com/wWolfovich/assher
Author: Oleg Marin
Author-email: wWolfovich@gmail.com
License: UNKNOWN
Keywords: AIO async SSH SFTP aioqs
Platform: UNKNOWN
Classifier: Programming Language :: Python :: 3
Classifier: License :: OSI Approved :: Apache Software License
Classifier: Operating System :: OS Independent
Requires-Python: >=3.6
Requires-Dist: aioqs (>=0.5.5)
Requires-Dist: asyncssh (>=1.12.0)
